mopidy_ytmusic/__init__.py
mopidy_ytmusic/backend.py
mopidy_ytmusic/command.py
mopidy_ytmusic/ext.conf
mopidy_ytmusic/library.py
mopidy_ytmusic/playback.py
mopidy_ytmusic/playlist.py
mopidy_ytmusic/repeating_timer.py
mopidy_ytmusic/scrobble_fe.py
mopidy_ytmusic-0.3.5.dist-info/entry_points.txt
mopidy_ytmusic-0.3.5.dist-info/LICENSE
mopidy_ytmusic-0.3.5.dist-info/WHEEL
mopidy_ytmusic-0.3.5.dist-info/METADATA
mopidy_ytmusic-0.3.5.dist-info/RECORD
