Metadata-Version: 2.1
Name: mopidy-ytmusic
Version: 0.3.5
Summary: Mopidy extension for playling music/managing playlists in Youtube Music
License: Apache-2.0
Author: Ozymandias (Tomas Ravinskas)
Author-email: tomas.rav@gmail.com
Requires-Python: >=3.7,<4.0
Classifier: License :: OSI Approved :: Apache Software License
Classifier: Programming Language :: Python :: 3
Classifier: Programming Language :: Python :: 3.10
Classifier: Programming Language :: Python :: 3.7
Classifier: Programming Language :: Python :: 3.8
Classifier: Programming Language :: Python :: 3.9
Requires-Dist: Mopidy (>=3,<4)
Requires-Dist: pytube (>=12.0.0,<13.0.0)
Requires-Dist: ytmusicapi (>=0.20.0,<0.21.0)
